nplusone/__init__.py
nplusone/core/__init__.py
nplusone/core/exceptions.py
nplusone/core/listeners.py
nplusone/core/notifiers.py
nplusone/core/signals.py
nplusone/core/stack.py
nplusone/ext/__init__.py
nplusone/ext/flask_sqlalchemy.py
nplusone/ext/peewee.py
nplusone/ext/sqlalchemy.py
nplusone/ext/django/__init__.py
nplusone/ext/django/middleware.py
nplusone/ext/django/patch.py
nplusone-0.9.0.dist-info/DESCRIPTION.rst
nplusone-0.9.0.dist-info/METADATA
nplusone-0.9.0.dist-info/RECORD
nplusone-0.9.0.dist-info/WHEEL
nplusone-0.9.0.dist-info/metadata.json
nplusone-0.9.0.dist-info/top_level.txt
