Metadata-Version: 2.0
Name: nplusone
Version: 0.9.0
Summary: Detecting the n+1 queries problem in Python
Home-page: https://github.com/jmcarp/nplusone
Author: Joshua Carp
Author-email: jm.carp@gmail.com
License: Copyright 2016 Joshua Carp
Requires-Dist: blinker (>=1.3)
Requires-Dist: six (>=1.9.0)
